commented_json/__init__.py
commented_json/encoder.py
commented_json-0.0.1.dist-info/LICENSE
commented_json-0.0.1.dist-info/WHEEL
commented_json-0.0.1.dist-info/METADATA
commented_json-0.0.1.dist-info/RECORD
